isonantic/__init__.py
isonantic/document.py
isonantic/exceptions.py
isonantic/fields.py
isonantic/models.py
isonantic/parsing.py
isonantic/py.typed
isonantic/schema.py
isonantic/validators.py
isonantic-1.0.1.dist-info/licenses/LICENSE
isonantic-1.0.1.dist-info/METADATA
isonantic-1.0.1.dist-info/WHEEL
isonantic-1.0.1.dist-info/top_level.txt
isonantic-1.0.1.dist-info/RECORD
