Metadata-Version: 2.4
Name: isonantic
Version: 1.0.1
Summary: ISONantic - A Pydantic-like data validation library for ISON format
Author: Mahesh Vaikri
Maintainer: Mahesh Vaikri
License: MIT
Project-URL: Homepage, https://www.ison.dev
Project-URL: Documentation, https://www.ison.dev
Project-URL: Repository, https://github.com/maheshvaikri-code/ison
Project-URL: Issues, https://github.com/maheshvaikri-code/ison/issues
Keywords: isonantic,ison,validation,pydantic,llm,ai,data-validation,type-safety,schema,structured-output
Classifier: Development Status :: 4 - Beta
Classifier: Intended Audience :: Developers
Classifier: License :: OSI Approved :: MIT License
Classifier: Operating System :: OS Independent
Classifier: Programming Language :: Python :: 3
Classifier: Programming Language :: Python :: 3.9
Classifier: Programming Language :: Python :: 3.10
Classifier: Programming Language :: Python :: 3.11
Classifier: Programming Language :: Python :: 3.12
Classifier: Topic :: Software Development :: Libraries :: Python Modules
Classifier: Topic :: Text Processing :: Markup
Classifier: Topic :: Scientific/Engineering :: Artificial Intelligence
Requires-Python: >=3.9
License-File: LICENSE
Requires-Dist: ison-py>=1.0.2
Provides-Extra: dev
Requires-Dist: pytest>=7.0; extra == "dev"
Requires-Dist: pytest-cov>=4.0; extra == "dev"
Requires-Dist: black>=23.0; extra == "dev"
Requires-Dist: isort>=5.0; extra == "dev"
Requires-Dist: mypy>=1.0; extra == "dev"
Dynamic: license-file
